describetable/Describetable.py
describetable/__init__.py
describetable/_imports_.py
describetable/describetable.min.js
describetable/describetable.min.js.map
describetable/main.css
describetable/metadata.json
describetable/package-info.json
describetable-0.0.7.dist-info/LICENSE
describetable-0.0.7.dist-info/METADATA
describetable-0.0.7.dist-info/WHEEL
describetable-0.0.7.dist-info/top_level.txt
describetable-0.0.7.dist-info/RECORD
