Metadata-Version: 2.1
Name: describetable
Version: 0.0.7
Summary: Project Description
Author: iglooDevelopment <andrew@igloodevelopment.dev>
License: MIT
Platform: UNKNOWN
Classifier: Framework :: Dash
License-File: LICENSE
